tachyon_api/__init__.py
tachyon_api/app.py
tachyon_api/background.py
tachyon_api/cache.py
tachyon_api/cli/__init__.py
tachyon_api/cli/__main__.py
tachyon_api/cli/commands/__init__.py
tachyon_api/cli/commands/generate.py
tachyon_api/cli/commands/lint.py
tachyon_api/cli/commands/new.py
tachyon_api/cli/commands/openapi.py
tachyon_api/cli/main.py
tachyon_api/cli/templates/__init__.py
tachyon_api/cli/templates/project.py
tachyon_api/cli/templates/service.py
tachyon_api/core/__init__.py
tachyon_api/core/lifecycle.py
tachyon_api/core/websocket.py
tachyon_api/di.py
tachyon_api/exceptions.py
tachyon_api/files.py
tachyon_api/middlewares/__init__.py
tachyon_api/middlewares/core.py
tachyon_api/middlewares/cors.py
tachyon_api/middlewares/logger.py
tachyon_api/models.py
tachyon_api/openapi.py
tachyon_api/params.py
tachyon_api/processing/__init__.py
tachyon_api/processing/dependencies.py
tachyon_api/processing/parameters.py
tachyon_api/processing/response_processor.py
tachyon_api/responses.py
tachyon_api/router.py
tachyon_api/security.py
tachyon_api/testing.py
tachyon_api/utils/__init__.py
tachyon_api/utils/type_converter.py
tachyon_api/utils/type_utils.py
tachyon_api-0.9.0.dist-info/METADATA
tachyon_api-0.9.0.dist-info/WHEEL
tachyon_api-0.9.0.dist-info/entry_points.txt
tachyon_api-0.9.0.dist-info/licenses/LICENSE
tachyon_api-0.9.0.dist-info/RECORD
