Metadata-Version: 2.4
Name: tachyon-api
Version: 0.9.0
Summary: A lightweight, FastAPI-inspired web framework
License: GPL-3.0-or-later
License-File: LICENSE
Author: Juan Manuel Panozzo Zénere
Author-email: jm.panozzozenere@gmail.com
Requires-Python: >=3.9,<3.14
Classifier: License :: OSI Approved :: GNU General Public License v3 or later (GPLv3+)
Classifier: Programming Language :: Python :: 3
Classifier: Programming Language :: Python :: 3.9
Classifier: Programming Language :: Python :: 3.10
Classifier: Programming Language :: Python :: 3.11
Classifier: Programming Language :: Python :: 3.12
Classifier: Programming Language :: Python :: 3.13
Requires-Dist: msgspec (>=0.19.0,<0.20.0)
Requires-Dist: orjson (>=3.11.1,<4.0.0)
Requires-Dist: python-multipart (>=0.0.20,<0.0.21)
Requires-Dist: ruff (==0.14.9)
Requires-Dist: starlette (>=0.47.2,<0.48.0)
Requires-Dist: typer (>=0.16.0,<0.17.0)
Requires-Dist: uvicorn (>=0.35.0,<0.36.0)
